TRecSys/__init__.py
TRecSys/__main__.py
TRecSys/encoders.py
TRecSys/endpoint.py
TRecSys/index_partitions.py
TRecSys/repartition.py
TRecSys/similarity_helpers.py
TRecSys/strategies.py
TRecSys/tree_helpers.py
TRecSys-0.2.72.dist-info/METADATA
TRecSys-0.2.72.dist-info/WHEEL
TRecSys-0.2.72.dist-info/top_level.txt
TRecSys-0.2.72.dist-info/RECORD
