Metadata-Version: 2.1
Name: TRecSys
Version: 0.2.72
Summary: UNKNOWN
Home-page: https://github.com/argmaxml/TRecs
Author: ArgmaxML
Author-email: uri@argmax.ml
License: UNKNOWN
Keywords: recommendation-systems,recsys,similarity-server
Platform: UNKNOWN
Requires-Dist: faiss-cpu (>=1.7.1.post3)
Requires-Dist: hnswlib (>=0.5.1)
Requires-Dist: numpy (>=1.21.2)
Requires-Dist: fastapi (>=0.68.0)
Requires-Dist: uvicorn (>=0.15.0)
Requires-Dist: smart-open[s3] (~=3.0.0)
Requires-Dist: joblib (>=0.17.0)
Requires-Dist: tqdm (>=4.62.3)
Requires-Dist: pandas (>=1.3.0)
